django_cte-stubs/__init__.pyi
django_cte-stubs/cte.pyi
django_cte-stubs/jitmixin.pyi
django_cte-stubs/join.pyi
django_cte-stubs/meta.pyi
django_cte-stubs/query.pyi
django_cte-stubs/raw.pyi
django_cte_stubs-1.1.0.dist-info/METADATA
django_cte_stubs-1.1.0.dist-info/WHEEL
django_cte_stubs-1.1.0.dist-info/licenses/LICENSE
django_cte_stubs-1.1.0.dist-info/RECORD
