Metadata-Version: 2.4
Name: django-cte-stubs
Version: 1.1.0
Summary: Mypy stubs for Django CTE
Project-URL: Homepage, https://github.com/moranabadie/django-cte-stubs
Project-URL: Release-notes, https://github.com/moranabadie/django-cte-stubs/releases
Author-email: Moran Abadie <moran.abadie@gmail.com>
Maintainer-email: Moran Abadie <moran.abadie@gmail.com>
License: BSD 3-Clause License
License-File: LICENSE
Keywords: code analysis,mypy,stubs,testing,typing
Classifier: Development Status :: 4 - Beta
Classifier: Framework :: Django
Classifier: Framework :: Django :: 4.1
Classifier: Framework :: Django :: 4.2
Classifier: Framework :: Django :: 5.2
Classifier: Intended Audience :: Developers
Classifier: License :: OSI Approved :: BSD License
Classifier: Operating System :: OS Independent
Classifier: Programming Language :: Python :: 3.9
Classifier: Programming Language :: Python :: 3.10
Classifier: Programming Language :: Python :: 3.11
Classifier: Programming Language :: Python :: 3.12
Classifier: Programming Language :: Python :: 3.13
Classifier: Typing :: Typed
Requires-Python: >=3.9
Requires-Dist: django-cte==2.*
Requires-Dist: django-stubs==5.*
Requires-Dist: mypy==1.*
